mlcrypto/__init__.py
mlcrypto/asymmetric.py
mlcrypto/cipher.py
mlcrypto/envelope.py
mlcrypto/kms.py
mlcrypto/kms_envelope.py
mlcrypto/multikey_envelope.py
mlcrypto/ssh_idnetity.py
mlcrypto/symmertric.py
mlcrypto/legacy/__init__.py
mlcrypto/legacy/aes_ctc.py
mlcrypto/legacy/kms_legacy_envelope.py
mlcrypto-0.6.297.dist-info/METADATA
mlcrypto-0.6.297.dist-info/RECORD
mlcrypto-0.6.297.dist-info/WHEEL
mlcrypto-0.6.297.dist-info/top_level.txt
