Metadata-Version: 2.1
Name: mlcrypto
Version: 0.6.297
Summary: pyCrypto wrapper, used by various MissingLink.ai libraries
Home-page: https://missinglink.ai
Author: MissingLink.ai
Author-email: support@missinglink.ai
License: UNKNOWN
Platform: UNKNOWN
Classifier: License :: OSI Approved :: MIT License
Classifier: Operating System :: OS Independent
Classifier: Programming Language :: Python
Classifier: Programming Language :: Python :: 3
Classifier: Programming Language :: Python :: 2.7
Provides-Extra: pycrypto
Provides-Extra: pycryptodomex
Requires-Dist: six
Requires-Dist: msgpack (~=0.5.6)
Provides-Extra: pycrypto
Requires-Dist: pycrypto (~=2.6.1); extra == 'pycrypto'
Provides-Extra: pycryptodomex
Requires-Dist: pycryptodome (~=3.6.4); extra == 'pycryptodomex'
